iglm/__init__.py
iglm/cli/__init__.py
iglm/cli/evaluate.py
iglm/cli/full_generation.py
iglm/cli/infill.py
iglm/model/IgLM.py
iglm/model/__init__.py
iglm/model/tokens.py
iglm/model/utils.py
iglm/trained_models/vocab.txt
iglm/trained_models/IgLM/config.json
iglm/trained_models/IgLM/pytorch_model.bin
iglm/trained_models/IgLM/training_args.bin
iglm/trained_models/IgLM-S/config.json
iglm/trained_models/IgLM-S/pytorch_model.bin
iglm/trained_models/IgLM-S/training_args.bin
iglm/utils/__init__.py
iglm/utils/general.py
iglm/utils/seed.py
iglm-0.1.0.dist-info/LICENSE.md
iglm-0.1.0.dist-info/METADATA
iglm-0.1.0.dist-info/WHEEL
iglm-0.1.0.dist-info/entry_points.txt
iglm-0.1.0.dist-info/top_level.txt
iglm-0.1.0.dist-info/RECORD
