Metadata-Version: 2.1
Name: iglm
Version: 0.1.0
License-File: LICENSE.md
Requires-Dist: biopython (>=1.79)
Requires-Dist: numpy (>=1.21.2)
Requires-Dist: tokenizers (>=0.10.2)
Requires-Dist: torch (>=1.11.0)
Requires-Dist: tqdm (>=4.64.0)
Requires-Dist: transformers (>=4.6.1)
